pysyntime/SynTime.py
pysyntime/__init__.py
pysyntime/model/BasicTaggedToken.py
pysyntime/model/TaggedToken.py
pysyntime/model/TimeSegment.py
pysyntime/model/TokenType.py
pysyntime/model/__init__.py
pysyntime/resource/SynTimeRegex.txt
pysyntime/util/NlpUtil.py
pysyntime/util/RegexUtil.py
pysyntime/util/TokenTypeUtil.py
pysyntime/util/__init__.py
pysyntime-1.0.0.dist-info/METADATA
pysyntime-1.0.0.dist-info/RECORD
pysyntime-1.0.0.dist-info/WHEEL
pysyntime-1.0.0.dist-info/top_level.txt
