Metadata-Version: 2.1
Name: pysyntime
Version: 1.0.0
Summary: SynTime implementation in Python.
Home-page: https://github.com/ZhouShengsheng/pysyntime
Author: Zhou Shengsheng
Author-email: szhou006@e.ntu.edu.sg
License: UNKNOWN
Platform: UNKNOWN
Classifier: Programming Language :: Python :: 3
Classifier: Programming Language :: Python :: 3.7
Requires-Dist: spacy (<3.0.0,>=2.0.0)
